SimpleS/__init__.py
SimpleS/detection.py
SimpleS/utils.py
SimpleS/ImageRelated/__init__.py
SimpleS/ImageRelated/basics.py
SimpleS/ImageRelated/enhancements.py
SimpleS/ImageRelated/tools.py
SimpleS/Points/Circle.py
SimpleS/Points/Dim2.py
SimpleS/Points/Dim3.py
SimpleS/Points/Line.py
SimpleS/Points/Triangle.py
SimpleS/Points/__init__.py
Simple_Space-3.2.0.dist-info/LICENSE
Simple_Space-3.2.0.dist-info/METADATA
Simple_Space-3.2.0.dist-info/WHEEL
Simple_Space-3.2.0.dist-info/top_level.txt
Simple_Space-3.2.0.dist-info/RECORD
