Metadata-Version: 2.1
Name: Simple-Space
Version: 3.2.0
Summary: A Try at Better Understanding Space.
Author-email: Hamed Hajipour <cloner174.org@gmail.com>
Project-URL: Homepage, https://github.com/cloner174/Simple-Space
Project-URL: Documentation, https://github.com/cloner174/Simple-Space#readme
Project-URL: Repository, https://github.com/cloner174/Simple-Space.git
Project-URL: Issues, https://github.com/cloner174/Simple-Space/issues
Classifier: Programming Language :: Python :: 3.6
Classifier: Programming Language :: Python :: 3.7
Classifier: Programming Language :: Python :: 3.8
Classifier: Programming Language :: Python :: 3.9
Classifier: Programming Language :: Python :: 3.10
Classifier: Programming Language :: Python :: 3.11
Classifier: License :: OSI Approved :: MIT License
Classifier: Operating System :: OS Independent
Requires-Python: >=3.6
License-File: LICENSE
Requires-Dist: numpy
Requires-Dist: matplotlib
Requires-Dist: pillow
Requires-Dist: scikit-image
Requires-Dist: scipy
Requires-Dist: opencv-python
